python_libratone_zipp/LibratoneMessage.py
python_libratone_zipp/LibratoneZipp.py
python_libratone_zipp/__init__.py
python_libratone_zipp/socket_hub.py
python_libratone_zipp-4.1.0.dist-info/licenses/LICENSE
python_libratone_zipp-4.1.0.dist-info/METADATA
python_libratone_zipp-4.1.0.dist-info/WHEEL
python_libratone_zipp-4.1.0.dist-info/top_level.txt
python_libratone_zipp-4.1.0.dist-info/RECORD
