Metadata-Version: 2.4
Name: python_libratone_zipp
Version: 4.1.0
Summary: Control one or multiple Libratone Zipp speakers with a Python library
Home-page: https://github.com/Chouffy/python_libratone_zipp
Author: Chouffy, Calyorbro
Author-email: git@chouffy.net
Project-URL: Bug Tracker, https://github.com/Chouffy/python_libratone_zipp/issues
Classifier: License :: OSI Approved :: MIT License
Classifier: Programming Language :: Python :: 3
Classifier: Operating System :: OS Independent
License-File: LICENSE
Dynamic: author
Dynamic: author-email
Dynamic: classifier
Dynamic: description
Dynamic: description-content-type
Dynamic: home-page
Dynamic: license-file
Dynamic: project-url
Dynamic: summary
